{
  "generated_at": "2026-06-07T16:44:58.420203+00:00",
  "count": 4,
  "sensors": [
    {
      "id": "sck-19236",
      "rawId": 19236,
      "source": "smartcitizen",
      "sourceLabel": "Smart Citizen",
      "name": "SCK@Jimbaran-2025",
      "lat": -8.79352,
      "lng": 115.14482,
      "lastReading": "2026-06-07T16:42:02Z",
      "reading": {
        "pm25": 11.8,
        "pm10": 12.4,
        "temp": 25.58,
        "rh": 58.78,
        "noise": 44.53
      },
      "detailsUrl": "https://smartcitizen.me/kits/19236"
    },
    {
      "id": "sck-19600",
      "rawId": 19600,
      "source": "smartcitizen",
      "sourceLabel": "Smart Citizen",
      "name": "SCK-TWO@Jimbaran-2025",
      "lat": -8.79351,
      "lng": 115.14472,
      "lastReading": "2026-06-07T16:43:19Z",
      "reading": {
        "pm25": 11.0,
        "pm10": 11.0,
        "temp": 23.78,
        "rh": 62.74,
        "noise": 49.7
      },
      "detailsUrl": "https://smartcitizen.me/kits/19600"
    },
    {
      "id": "sck-19618",
      "rawId": 19618,
      "source": "smartcitizen",
      "sourceLabel": "Smart Citizen",
      "name": "SCK-THREE@Jimbaran-2025",
      "lat": -8.79533,
      "lng": 115.14784,
      "lastReading": "2026-06-07T16:44:04Z",
      "reading": {
        "pm25": 11.7,
        "pm10": 12.0,
        "temp": 23.52,
        "rh": 59.42,
        "noise": 46.01
      },
      "detailsUrl": "https://smartcitizen.me/kits/19618"
    },
    {
      "id": "sck-19651",
      "rawId": 19651,
      "source": "smartcitizen",
      "sourceLabel": "Smart Citizen",
      "name": "Bali DIY Node — Office",
      "lat": -8.79314,
      "lng": 115.14467,
      "lastReading": "2026-06-07T16:44:33Z",
      "reading": {
        "pm25": 6.0,
        "pm10": 6.0,
        "temp": 28.89619,
        "rh": 44.84718,
        "noise": null
      },
      "detailsUrl": "https://smartcitizen.me/kits/19651"
    }
  ]
}